{
  "project_info": {
    "project_number": "1014839599210",
    "project_id": "chatapplication-ad3b1",
    "storage_bucket": "chatapplication-ad3b1.firebasestorage.app"
  },
  "client": [
    {
      "client_info": {
        "mobilesdk_app_id": "1:1014839599210:android:d70a82b53fbf5ff3c7aa13",
        "android_client_info": {
          "package_name": "com.saravanan.chatapplication"
        }
      },
      "oauth_client": [],
      "api_key": [
        {
          "current_key": "AIzaSyBauerIWF5_9UB1avKPIGKsJwGjHxD4bJs"
        }
      ],
      "services": {
        "appinvite_service": {
          "other_platform_oauth_client": []
        }
      }
    }
  ],
  "configuration_version": "1"
}